LICENSE
MANIFEST.in
README.md
setup.py
gazar/__init__.py
gazar/grid.py
gazar/log.py
gazar/meta.py
gazar/shape.py
gazar.egg-info/PKG-INFO
gazar.egg-info/SOURCES.txt
gazar.egg-info/dependency_links.txt
gazar.egg-info/requires.txt
gazar.egg-info/top_level.txt