Metadata-Version: 1.1
Name: gazar
Version: 0.0.4
Summary: A collection of functions to use with GDAL.
Home-page: https://github.com/snowman2/gazar
Author: Alan D. Snow
Author-email: alansnow21@gmail.com
License: BSD 3-Clause
Keywords: gdal
Platform: UNKNOWN
Classifier: Intended Audience :: Developers
Classifier: Intended Audience :: Science/Research
Classifier: Operating System :: OS Independent
Classifier: Programming Language :: Python
Classifier: Programming Language :: Python :: 2
Classifier: Programming Language :: Python :: 2.7
Classifier: Programming Language :: Python :: 3
Classifier: Programming Language :: Python :: 3.5
Classifier: Programming Language :: Python :: 3.6
